ocean_data_gateway/__init__.py
ocean_data_gateway/_version.py
ocean_data_gateway/gateway.py
ocean_data_gateway/readers/__init__.py
ocean_data_gateway/readers/axds.py
ocean_data_gateway/readers/erddap.py
ocean_data_gateway/readers/local.py
ocean_data_gateway-21.dist-info/LICENSE.txt
ocean_data_gateway-21.dist-info/METADATA
ocean_data_gateway-21.dist-info/WHEEL
ocean_data_gateway-21.dist-info/top_level.txt
ocean_data_gateway-21.dist-info/RECORD
