Metadata-Version: 2.1
Name: ocean-data-gateway
Version: 21
Summary: Your gateway to ocean data.
Home-page: https://github.com/axiom-data-science/ocean_data_gateway
Author: Kristen Thyng
Author-email: kristen@axds.co
License: MIT
Platform: UNKNOWN
Classifier: Development Status :: 5 - Production/Stable
Classifier: Topic :: Scientific/Engineering
Classifier: Intended Audience :: Science/Research
Classifier: Operating System :: OS Independent
Classifier: Programming Language :: Python
Classifier: Programming Language :: Python :: 3
Classifier: Programming Language :: Python :: 3.6
Classifier: Programming Language :: Python :: 3.7
Classifier: Programming Language :: Python :: 3.8
Classifier: License :: OSI Approved :: MIT License
Requires-Python: >=3.6
License-File: LICENSE.txt
Requires-Dist: jupyter
Requires-Dist: jupyterlab
Requires-Dist: numpy
Requires-Dist: scipy
Requires-Dist: dask
Requires-Dist: netcdf4
Requires-Dist: matplotlib
Requires-Dist: joblib
Requires-Dist: shapely
Requires-Dist: intake
Requires-Dist: pandas
Requires-Dist: xarray
Requires-Dist: requests
Requires-Dist: flake8
Requires-Dist: isort
Requires-Dist: erddapy
Requires-Dist: pytest
Requires-Dist: ipython
Requires-Dist: aiohttp
Requires-Dist: intake-xarray
